LICENSE.txt
MANIFEST.in
PKG-INFO
README.rst
pyproject.toml
setup.cfg
setup.py
dispy.egg-info/PKG-INFO
dispy.egg-info/SOURCES.txt
dispy.egg-info/dependency_links.txt
dispy.egg-info/requires.txt
dispy.egg-info/top_level.txt
py2/__init__.py
py2/config.py
py2/dispy_cmd.py
py2/dispyadmin.py
py2/dispynetrelay.py
py2/dispynode.py
py2/dispyscheduler.py
py2/httpd.py
py2/data/Dockerfile
py2/data/admin.html
py2/data/admin_node.html
py2/data/dispy.css
py2/data/dispy.js
py2/data/favicon.ico
py2/data/jquery.js
py2/data/manage.html
py2/data/monitor.html
py2/data/node.html
py2/examples/bounded_submit.py
py2/examples/delegate.py
py2/examples/httpd_example.py
py2/examples/job_scheduler.py
py2/examples/longrun.py
py2/examples/node_setup.py
py2/examples/node_shvars.py
py2/examples/node_update.py
py2/examples/node_update_script.py
py2/examples/obj_instances.py
py2/examples/provisional_results.py
py2/examples/replace_inmem.py
py2/examples/sample.py
py2/examples/sshportfw.py
py3/__init__.py
py3/config.py
py3/dispy_cmd.py
py3/dispyadmin.py
py3/dispynetrelay.py
py3/dispynode.py
py3/dispyscheduler.py
py3/httpd.py
py3.7/__init__.py
py3.7/config.py
py3.7/dispy_cmd.py
py3.7/dispyadmin.py
py3.7/dispynetrelay.py
py3.7/dispynode.py
py3.7/dispyscheduler.py
py3.7/httpd.py
py3.7/data/Dockerfile
py3.7/data/admin.html
py3.7/data/admin_node.html
py3.7/data/dispy.css
py3.7/data/dispy.js
py3.7/data/favicon.ico
py3.7/data/jquery.js
py3.7/data/manage.html
py3.7/data/monitor.html
py3.7/data/node.html
py3.7/examples/bounded_submit.py
py3.7/examples/delegate.py
py3.7/examples/httpd_example.py
py3.7/examples/job_scheduler.py
py3.7/examples/longrun.py
py3.7/examples/node_setup.py
py3.7/examples/node_shvars.py
py3.7/examples/node_update.py
py3.7/examples/node_update_script.py
py3.7/examples/obj_instances.py
py3.7/examples/provisional_results.py
py3.7/examples/replace_inmem.py
py3.7/examples/sample.py
py3.7/examples/sshportfw.py
py3/data/Dockerfile
py3/data/admin.html
py3/data/admin_node.html
py3/data/dispy.css
py3/data/dispy.js
py3/data/favicon.ico
py3/data/jquery.js
py3/data/manage.html
py3/data/monitor.html
py3/data/node.html
